dju_common/__init__.py
dju_common/constants.py
dju_common/context_processors.py
dju_common/cyclictask_core.py
dju_common/db.py
dju_common/decorators.py
dju_common/file.py
dju_common/gravatar.py
dju_common/http.py
dju_common/mail.py
dju_common/modeltranslation.py
dju_common/paginator.py
dju_common/serializers.py
dju_common/settings.py
dju_common/tcache.py
dju_common/tools.py
dju_common/validators.py
dju_common/fields/__init__.py
dju_common/fields/json.py
dju_common/fields/o2o.py
dju_common/forms/__init__.py
dju_common/forms/bootstrap.py
dju_common/forms/helpers.py
dju_common/locale/en/LC_MESSAGES/django.mo
dju_common/locale/en/LC_MESSAGES/django.po
dju_common/locale/ru/LC_MESSAGES/django.mo
dju_common/locale/ru/LC_MESSAGES/django.po
dju_common/locale/uk/LC_MESSAGES/django.mo
dju_common/locale/uk/LC_MESSAGES/django.po
dju_common/management/__init__.py
dju_common/management/commands/__init__.py
dju_common/management/commands/dju_clear_cache.py
dju_common/management/commands/dju_compilemessages.py
dju_common/management/commands/dju_custom_django_makemessages.py
dju_common/management/commands/dju_debug_email_server.py
dju_common/management/commands/dju_makemessages.py
dju_common/management/commands/dju_send_test_email.py
dju_common/static/bootstrap-3.3.5/css/bootstrap-theme.css
dju_common/static/bootstrap-3.3.5/css/bootstrap-theme.css.map
dju_common/static/bootstrap-3.3.5/css/bootstrap-theme.min.css
dju_common/static/bootstrap-3.3.5/css/bootstrap.css
dju_common/static/bootstrap-3.3.5/css/bootstrap.css.map
dju_common/static/bootstrap-3.3.5/css/bootstrap.min.css
dju_common/static/bootstrap-3.3.5/fonts/glyphicons-halflings-regular.eot
dju_common/static/bootstrap-3.3.5/fonts/glyphicons-halflings-regular.svg
dju_common/static/bootstrap-3.3.5/fonts/glyphicons-halflings-regular.ttf
dju_common/static/bootstrap-3.3.5/fonts/glyphicons-halflings-regular.woff
dju_common/static/bootstrap-3.3.5/fonts/glyphicons-halflings-regular.woff2
dju_common-0.4.2.dist-info/DESCRIPTION.rst
dju_common-0.4.2.dist-info/METADATA
dju_common-0.4.2.dist-info/RECORD
dju_common-0.4.2.dist-info/WHEEL
dju_common-0.4.2.dist-info/metadata.json
dju_common-0.4.2.dist-info/top_level.txt
