Metadata-Version: 2.0
Name: dju-common
Version: 0.4.2
Summary: Django Utils: Common Library
Home-page: https://github.com/liminspace/dju-common
Author: Igor Melnyk @liminspace
Author-email: liminspace@gmail.com
License: MIT
Platform: UNKNOWN
Requires-Dist: django (>=1.8,<1.12)
Requires-Dist: simplejson
